{"blocks":[{"x":770,"y":400,"text":"\t\ts += h * ((pow(cos(x), 3) - 4) + (pow(cos(x+h), 3) - 4)) / 2;\r\n\t\tx += h;","width":380,"height":80,"type":"Блок","isMenuBlock":false,"fontSize":14,"textHeight":14,"isBold":false,"isItalic":false,"textAlign":"center","labelsPosition":1},{"x":770,"y":490,"text":"x < (b - h)","width":380,"height":40,"type":"Условие","isMenuBlock":false,"fontSize":14,"textHeight":14,"isBold":false,"isItalic":false,"textAlign":"center","labelsPosition":1},{"x":770,"y":570,"text":"s","width":380,"height":40,"type":"Ввод / вывод","isMenuBlock":false,"fontSize":14,"textHeight":14,"isBold":false,"isItalic":false,"textAlign":"center","labelsPosition":1},{"x":770,"y":630,"text":"конец","width":380,"height":30,"type":"Начало / конец","isMenuBlock":false,"fontSize":14,"textHeight":14,"isBold":false,"isItalic":false,"textAlign":"center","labelsPosition":1},{"x":770,"y":290,"text":"\th = (b - a) / n;\r\n\tx = a;\r\n\ts = 0;","width":380,"height":60,"type":"Блок","isMenuBlock":false,"fontSize":14,"textHeight":14,"isBold":false,"isItalic":false,"textAlign":"center","labelsPosition":1},{"x":1110,"y":250,"text":"laba8Trap","width":80,"height":20,"type":"Текст / комментарий","isMenuBlock":false,"fontSize":14,"textHeight":14,"isBold":false,"isItalic":false,"textAlign":"left","labelsPosition":1},{"x":770,"y":210,"text":"float s, a = 4,\n b = 7, h, x, n = 200;\r","width":380,"height":60,"type":"Блок","isMenuBlock":false,"fontSize":14,"textHeight":14,"isBold":false,"isItalic":false,"textAlign":"center","labelsPosition":1},{"x":770,"y":130,"text":"начало","width":380,"height":30,"type":"Начало / конец","isMenuBlock":false,"fontSize":14,"textHeight":14,"isBold":false,"isItalic":false,"textAlign":"center","labelsPosition":1}],"arrows":[{"startIndex":7,"endIndex":6,"startConnectorIndex":2,"endConnectorIndex":0,"nodes":[{"x":770,"y":145},{"x":770,"y":160},{"x":770,"y":180}],"counts":[1,1,1]},{"startIndex":6,"endIndex":4,"startConnectorIndex":2,"endConnectorIndex":0,"nodes":[{"x":770,"y":240},{"x":770,"y":240},{"x":770,"y":260}],"counts":[1,1,1]},{"startIndex":4,"endIndex":0,"startConnectorIndex":2,"endConnectorIndex":0,"nodes":[{"x":770,"y":320},{"x":770,"y":340},{"x":770,"y":360}],"counts":[1,1,1]},{"startIndex":0,"endIndex":1,"startConnectorIndex":2,"endConnectorIndex":0,"nodes":[{"x":770,"y":440},{"x":770,"y":450},{"x":770,"y":470}],"counts":[1,1,1]},{"startIndex":2,"endIndex":3,"startConnectorIndex":2,"endConnectorIndex":0,"nodes":[{"x":770,"y":590},{"x":770,"y":600},{"x":770,"y":615}],"counts":[1,1,1]},{"startIndex":1,"endIndex":2,"startConnectorIndex":3,"endConnectorIndex":0,"nodes":[{"x":580,"y":490},{"x":560,"y":490},{"x":560,"y":530},{"x":770,"y":530},{"x":770,"y":550}],"counts":[1,1,1,1,1]},{"startIndex":1,"endIndex":0,"startConnectorIndex":1,"endConnectorIndex":0,"nodes":[{"x":960,"y":490},{"x":970,"y":490},{"x":970,"y":340},{"x":770,"y":340},{"x":770,"y":360}],"counts":[1,1,1,1,1]}],"x0":78.5,"y0":-79.5}